ra_rem/__init__.py
ra_rem/api/__init__.py
ra_rem/api/building_profiler_api.py
ra_rem/api/residential_electrification_model_api.py
ra_rem/api_client.py
ra_rem/api_response.py
ra_rem/configuration.py
ra_rem/exceptions.py
ra_rem/models/__init__.py
ra_rem/models/building_features.py
ra_rem/models/building_profile.py
ra_rem/models/fuel_data.py
ra_rem/models/fuel_data_rates.py
ra_rem/models/heating_fuel.py
ra_rem/models/http_validation_error.py
ra_rem/models/impact.py
ra_rem/models/metrics.py
ra_rem/models/rem_profile_request.py
ra_rem/models/savings.py
ra_rem/models/valid_upgrade.py
ra_rem/models/validation_error.py
ra_rem/models/validation_error_loc_inner.py
ra_rem/py.typed
ra_rem/rest.py
ra_rem-0.1.8.dist-info/LICENSE.md
ra_rem-0.1.8.dist-info/METADATA
ra_rem-0.1.8.dist-info/WHEEL
ra_rem-0.1.8.dist-info/RECORD
