Metadata-Version: 2.1
Name: ra_rem
Version: 0.1.8
Summary: Python client stubs for the REM (Residential Electrification Model) API
Home-page: https://github.com/rewiringamerica/ra-api-rem-py
License: LICENSE.md
Keywords: Rewiring America,REM,electrification,utility,energy,emissions,savings
Author: OpenAPI Generator Community
Author-email: team@openapitools.org
Requires-Python: >=3.8,<4.0
Classifier: License :: Other/Proprietary License
Classifier: Programming Language :: Python :: 3
Classifier: Programming Language :: Python :: 3.8
Classifier: Programming Language :: Python :: 3.9
Classifier: Programming Language :: Python :: 3.10
Classifier: Programming Language :: Python :: 3.11
Classifier: Programming Language :: Python :: 3.12
Classifier: Programming Language :: Python :: 3.13
Requires-Dist: keyrings-google-artifactregistry-auth (>=1.1.2,<2.0.0)
Requires-Dist: pydantic (>=2)
Requires-Dist: python-dateutil (>=2.8.2)
Requires-Dist: typing-extensions (>=4.7.1)
Requires-Dist: urllib3 (>=1.25.3,<3.0.0)
Project-URL: Repository, https://github.com/rewiringamerica/ra-api-rem-py
